win32more/Microsoft/__init__.py
win32more/appsdk/__init__.py
win32more/appsdk/_packaging.py
win32more/appsdk/_runtime.py
win32more/appsdk/mddbootstrap.py
win32more/winui3/__init__.py
win32more/winui3/app.xaml
win32more_appsdk-0.8.0.dist-info/METADATA
win32more_appsdk-0.8.0.dist-info/WHEEL
win32more_appsdk-0.8.0.dist-info/RECORD
